README.md
setup.py
ashu_topsis/__init__.py
ashu_topsis/run.py
ashu_topsis/topsis.py
ashu_topsis.egg-info/PKG-INFO
ashu_topsis.egg-info/SOURCES.txt
ashu_topsis.egg-info/dependency_links.txt
ashu_topsis.egg-info/top_level.txt