Metadata-Version: 2.1
Name: ashu-topsis
Version: 0.0.1
Summary: A small example package
Home-page: https://github.com/ashutosh2539/topsis
Author: Ashutosh Gupta
Author-email: agupta12_be17@thapar.edu
License: UNKNOWN
Download-URL: https://github.com/ashutosh2539/ashu_topsis.git
Platform: UNKNOWN
Classifier: Programming Language :: Python :: 3
Classifier: License :: OSI Approved :: MIT License
Classifier: Operating System :: OS Independent
Requires-Python: >=3.6
